<?xml version="1.0" encoding="utf-8"?>
<Entity parent="template_structure_civic_civil_centre">
  <Health>
    <SpawnEntityOnDeath>decay|rubble/rubble_hele_cc</SpawnEntityOnDeath>
  </Health>
  <Identity>
    <Civ>athen</Civ>
    <SpecificName>Agorá</SpecificName>
  </Identity>
  <Upgrade>
    <CC>
      <Entity>structures/athen_civil_centre_a</Entity>
      <Tooltip></Tooltip>
      <RequiredTechnology>phase_village</RequiredTechnology>
      <Cost>
        <wood>0</wood>
        <stone>0</stone>
      </Cost>
      <Time>10</Time>
    </CC>
  </Upgrade>
  <VisualActor>
    <Actor>structures/athenians/civil_centre_b.xml</Actor>
  </VisualActor>
</Entity>
